<?xml version="1.0" encoding="UTF-8"?>
<jcr:root xmlns:cq="http://www.day.com/jcr/cq/1.0" xmlns:jcr="http://www.jcp.org/jcr/1.0" xmlns:nt="http://www.jcp.org/jcr/nt/1.0"
    jcr:primaryType="cq:Dialog"
    height="600"
    title="Global Properties"
    width="950"
    xtype="dialog">
    <items
        jcr:primaryType="cq:Widget"
        xtype="tabpanel">
        <items jcr:primaryType="cq:WidgetCollection">
            <tab1
                jcr:primaryType="cq:Panel"
                title="Mega Menu">
                <items jcr:primaryType="cq:WidgetCollection">
                    <bottomsection
                        jcr:primaryType="cq:Widget"
                        collapsed="{Boolean}true"
                        collapsible="{Boolean}true"
                        title="Bottom Section"
                        xtype="dialogfieldset">
                        <items jcr:primaryType="cq:WidgetCollection">
                            <pages
                                jcr:primaryType="cq:Widget"
                                addItemLabel="Add Zone"
                                anchor="95%"
                                fieldDescription="Click the '+' to add a new zone"
                                fieldLabel="Zones"
                                hideLabel="false"
                                maxItems="{Long}4"
                                name="./bottomSection"
                                xtype="multifield">
                                <fieldConfig
                                    jcr:primaryType="cq:Widget"
                                    xtype="multifieldpanel">
                                    <items jcr:primaryType="cq:WidgetCollection">
                                        <label
                                            jcr:primaryType="nt:unstructured"
                                            allowBlank="false"
                                            anchor="95%"
                                            fieldLabel="Label"
                                            key="label"
                                            validateOnBlur="true"
                                            xtype="textfield"/>
                                        <link
                                            jcr:primaryType="cq:Widget"
                                            anchor="95%"
                                            fieldLabel="Link"
                                            key="link"
                                            linkPattern="\{0}.html"
                                            xtype="pathfield"/>
                                        <links
                                            jcr:primaryType="cq:Widget"
                                            addItemLabel="Add Link"
                                            fieldDescription="Click the '+' to add a new link"
                                            fieldLabel="Links"
                                            key="links"
                                            maxItems="{Long}7"
                                            minItems="{Long}1"
                                            xtype="multifield">
                                            <fieldConfig
                                                jcr:primaryType="cq:Widget"
                                                xtype="multifieldpanel">
                                                <items jcr:primaryType="cq:WidgetCollection">
                                                    <label
                                                        jcr:primaryType="nt:unstructured"
                                                        allowBlank="false"
                                                        anchor="98%"
                                                        fieldLabel="Label"
                                                        key="label"
                                                        validateOnBlur="true"
                                                        xtype="textfield"/>
                                                    <link
                                                        jcr:primaryType="cq:Widget"
                                                        allowBlank="false"
                                                        anchor="98%"
                                                        fieldLabel="Link"
                                                        key="link"
                                                        linkPattern="\{0}.html"
                                                        xtype="pathfield"/>
                                                </items>
                                            </fieldConfig>
                                        </links>
                                    </items>
                                </fieldConfig>
                            </pages>
                        </items>
                    </bottomsection>
                    <topsection
                        jcr:primaryType="cq:Widget"
                        collapsed="{Boolean}false"
                        collapsible="{Boolean}true"
                        title="Top Section"
                        xtype="dialogfieldset">
                        <items jcr:primaryType="cq:WidgetCollection">
                            <pages
                                jcr:primaryType="cq:Widget"
                                addItemLabel="Add Zone"
                                anchor="95%"
                                fieldDescription="Click the '+' to add a new zone"
                                fieldLabel="Zones"
                                hideLabel="false"
                                maxItems="{Long}3"
                                name="./topSection"
                                xtype="multifield">
                                <fieldConfig
                                    jcr:primaryType="cq:Widget"
                                    xtype="multifieldpanel">
                                    <items jcr:primaryType="cq:WidgetCollection">
                                        <label
                                            jcr:primaryType="nt:unstructured"
                                            allowBlank="false"
                                            anchor="95%"
                                            fieldLabel="Label"
                                            key="label"
                                            validateOnBlur="true"
                                            xtype="textfield"/>
                                        <link
                                            jcr:primaryType="cq:Widget"
                                            anchor="95%"
                                            fieldLabel="Link"
                                            key="link"
                                            linkPattern="\{0}.html"
                                            xtype="pathfield"/>
                                        <links
                                            jcr:primaryType="cq:Widget"
                                            addItemLabel="Add Link"
                                            fieldDescription="Click the '+' to add a new link"
                                            fieldLabel="Links"
                                            key="links"
                                            maxItems="{Long}8"
                                            minItems="{Long}1"
                                            xtype="multifield">
                                            <fieldConfig
                                                jcr:primaryType="cq:Widget"
                                                xtype="multifieldpanel">
                                                <items jcr:primaryType="cq:WidgetCollection">
                                                    <label
                                                        jcr:primaryType="nt:unstructured"
                                                        allowBlank="false"
                                                        anchor="98%"
                                                        fieldLabel="Label"
                                                        key="label"
                                                        validateOnBlur="true"
                                                        xtype="textfield"/>
                                                    <link
                                                        jcr:primaryType="cq:Widget"
                                                        allowBlank="false"
                                                        anchor="98%"
                                                        fieldLabel="Link"
                                                        key="link"
                                                        linkPattern="\{0}.html"
                                                        xtype="pathfield"/>
                                                </items>
                                            </fieldConfig>
                                        </links>
                                    </items>
                                </fieldConfig>
                            </pages>
                        </items>
                    </topsection>
                </items>
            </tab1>
            <header
                jcr:primaryType="cq:Panel"
                title="Header">
                <items jcr:primaryType="cq:WidgetCollection">
                    <logo
                        jcr:primaryType="cq:Widget"
                        collapsed="{Boolean}false"
                        collapsible="{Boolean}true"
                        title="Logo"
                        xtype="dialogfieldset">
                        <items jcr:primaryType="cq:WidgetCollection">
                            <image
                                jcr:primaryType="cq:Widget"
                                allowBlank="false"
                                anchor="95%"
                                ddGroups="[media]"
                                fieldLabel="Image"
                                name="./logo/image/fileReference"
                                rootPath="/content/dam"
                                rootTitle="Assets"
                                xtype="pathfield"/>
                            <link
                                jcr:primaryType="cq:Widget"
                                anchor="95%"
                                fieldLabel="Link"
                                linkPattern="\{0}.html"
                                name="./logoLink"
                                rootPath="/content/metlife"
                                rootTitle="MetLife"
                                xtype="pathfield"/>
                            <alt
                                jcr:primaryType="cq:Widget"
                                anchor="95%"
                                fieldLabel="Alt Text"
                                name="./logoAltText"
                                xtype="textfield"/>
                            <imageresourcetype
                                jcr:primaryType="cq:Widget"
                                ignoreData="true"
                                name="./logo/image/sling:resourceType"
                                value="foundation/components/image"
                                xtype="hidden"/>
                        </items>
                    </logo>
                    <megamenu
                        jcr:primaryType="cq:Widget"
                        collapsed="{Boolean}true"
                        collapsible="{Boolean}true"
                        title="Mega Menu"
                        xtype="dialogfieldset">
                        <items jcr:primaryType="cq:WidgetCollection">
                            <label
                                jcr:primaryType="cq:Widget"
                                anchor="95%"
                                fieldLabel="Label"
                                name="./megaMenuLabel"
                                xtype="textfield"/>
                            <image
                                jcr:primaryType="cq:Widget"
                                anchor="95%"
                                ddGroups="[media]"
                                fieldLabel="Image"
                                name="./megaMenu/image/fileReference"
                                rootPath="/content/dam"
                                rootTitle="Assets"
                                xtype="pathfield"/>
                            <imageresourcetype
                                jcr:primaryType="cq:Widget"
                                ignoreData="true"
                                name="./megaMenu/image/sling:resourceType"
                                value="foundation/components/image"
                                xtype="hidden"/>
                        </items>
                    </megamenu>
                    <close
                        jcr:primaryType="cq:Widget"
                        collapsed="{Boolean}true"
                        collapsible="{Boolean}true"
                        title="Close Button"
                        xtype="dialogfieldset">
                        <items jcr:primaryType="cq:WidgetCollection">
                            <label
                                jcr:primaryType="cq:Widget"
                                anchor="95%"
                                fieldLabel="Label"
                                name="./closeLabel"
                                xtype="textfield"/>
                            <image
                                jcr:primaryType="cq:Widget"
                                anchor="95%"
                                ddGroups="[media]"
                                fieldLabel="Image"
                                name="./close/image/fileReference"
                                rootPath="/content/dam"
                                rootTitle="Assets"
                                xtype="pathfield"/>
                            <imageresourcetype
                                jcr:primaryType="cq:Widget"
                                ignoreData="true"
                                name="./close/image/sling:resourceType"
                                value="foundation/components/image"
                                xtype="hidden"/>
                        </items>
                    </close>
                    <home
                        jcr:primaryType="cq:Widget"
                        collapsed="{Boolean}true"
                        collapsible="{Boolean}true"
                        title="Home"
                        xtype="dialogfieldset">
                        <items jcr:primaryType="cq:WidgetCollection">
                            <label
                                jcr:primaryType="cq:Widget"
                                anchor="95%"
                                fieldLabel="Label"
                                name="./homeLabel"
                                xtype="textfield"/>
                            <image
                                jcr:primaryType="cq:Widget"
                                anchor="95%"
                                ddGroups="[media]"
                                fieldLabel="Image"
                                name="./home/image/fileReference"
                                rootPath="/content/dam"
                                rootTitle="Assets"
                                xtype="pathfield"/>
                            <imageresourcetype
                                jcr:primaryType="cq:Widget"
                                ignoreData="true"
                                name="./home/image/sling:resourceType"
                                value="foundation/components/image"
                                xtype="hidden"/>
                            <link
                                jcr:primaryType="cq:Widget"
                                anchor="95%"
                                fieldLabel="Link"
                                linkPattern="\{0}.html"
                                name="./homeLink"
                                rootPath="/content/metlife"
                                rootTitle="MetLife"
                                xtype="pathfield"/>
                        </items>
                    </home>
                    <search
                        jcr:primaryType="cq:Widget"
                        collapsed="{Boolean}true"
                        collapsible="{Boolean}true"
                        title="Search"
                        xtype="dialogfieldset">
                        <items jcr:primaryType="cq:WidgetCollection">
                            <label
                                jcr:primaryType="cq:Widget"
                                anchor="95%"
                                fieldLabel="Label"
                                name="./searchLabel"
                                xtype="textfield"/>
                            <image
                                jcr:primaryType="cq:Widget"
                                anchor="95%"
                                ddGroups="[media]"
                                fieldLabel="Image"
                                name="./search/image/fileReference"
                                rootPath="/content/dam"
                                rootTitle="Assets"
                                xtype="pathfield"/>
                            <imageresourcetype
                                jcr:primaryType="cq:Widget"
                                ignoreData="true"
                                name="./search/image/sling:resourceType"
                                value="foundation/components/image"
                                xtype="hidden"/>
                            <placeholder
                                jcr:primaryType="cq:Widget"
                                anchor="95%"
                                fieldLabel="Placeholder Label"
                                name="./searchPlaceholderLabel"
                                xtype="textfield"/>
                            <imageform
                                jcr:primaryType="cq:Widget"
                                anchor="95%"
                                ddGroups="[media]"
                                fieldLabel="Image Form"
                                name="./search/imageForm/fileReference"
                                rootPath="/content/dam"
                                rootTitle="Assets"
                                xtype="pathfield"/>
                            <imageformresourcetype
                                jcr:primaryType="cq:Widget"
                                ignoreData="true"
                                name="./search/imageForm/sling:resourceType"
                                value="foundation/components/image"
                                xtype="hidden"/>
                            <link
                                jcr:primaryType="cq:Widget"
                                anchor="95%"
                                fieldLabel="Results Page Link"
                                linkPattern="\{0}.html"
                                name="./searchLink"
                                rootPath="/content/metlife"
                                rootTitle="MetLife"
                                xtype="pathfield"/>
                        </items>
                    </search>
                </items>
            </header>
            <footer
                jcr:primaryType="cq:Panel"
                title="Footer">
                <items jcr:primaryType="cq:WidgetCollection">
                    <footerlogo
                        jcr:primaryType="cq:Widget"
                        collapsed="{Boolean}false"
                        collapsible="{Boolean}true"
                        title="Footer Logo"
                        xtype="dialogfieldset">
                        <items jcr:primaryType="cq:WidgetCollection">
                            <image
                                jcr:primaryType="cq:Widget"
                                allowBlank="false"
                                anchor="95%"
                                ddGroups="[media]"
                                fieldLabel="Image"
                                name="./footer/image/fileReference"
                                rootPath="/content/dam"
                                rootTitle="Assets"
                                xtype="pathfield"/>
                            <labellink
                                jcr:primaryType="cq:Widget"
                                anchor="95%"
                                fieldLabel="Label"
                                name="./footerLogoLabel"
                                xtype="textfield"/>
                            <link
                                jcr:primaryType="cq:Widget"
                                anchor="95%"
                                fieldLabel="Link"
                                linkPattern="\{0}.html"
                                name="./footerlogoLink"
                                rootPath="/content/metlife"
                                rootTitle="MetLife"
                                xtype="pathfield"/>
                            <alt
                                jcr:primaryType="cq:Widget"
                                anchor="95%"
                                fieldLabel="Alt Text"
                                name="./footerlogoAltText"
                                xtype="textfield"/>
                            <imageresourcetype
                                jcr:primaryType="cq:Widget"
                                ignoreData="true"
                                name="./footer/image/sling:resourceType"
                                value="foundation/components/image"
                                xtype="hidden"/>
                        </items>
                    </footerlogo>
                    <bullets
                        jcr:primaryType="cq:Widget"
                        addItemLabel="Add Bullet"
                        fieldDescription="Click the '+' to add a new bullet"
                        fieldLabel="Footer Bullets"
                        hideLabel="false"
                        name="./footerbulletlinks"
                        xtype="multifield">
                        <fieldConfig
                            jcr:primaryType="cq:Widget"
                            xtype="multifieldpanel">
                            <items jcr:primaryType="cq:WidgetCollection">
                                <A_title
                                    jcr:primaryType="nt:unstructured"
                                    allowBlank="false"
                                    fieldLabel="Label"
                                    key="navigationTitle"
                                    validateOnBlur="true"
                                    xtype="textfield"/>
                                <C_pages
                                    jcr:primaryType="cq:Widget"
                                    allowBlank="false"
                                    anchor="100%"
                                    fieldLabel="URL"
                                    key="path"
                                    linkPattern="\{0}.html"
                                    rootPath="/content/metlife"
                                    xtype="pathfield"/>
                                <D_target
                                    jcr:primaryType="cq:Widget"
                                    allowBlank="false"
                                    defaultValue="_self"
                                    fieldLabel="Target"
                                    key="target"
                                    type="select"
                                    xtype="selection">
                                    <options jcr:primaryType="cq:WidgetCollection">
                                        <self
                                            jcr:primaryType="nt:unstructured"
                                            text="Same Page"
                                            value="_self"/>
                                        <blank
                                            jcr:primaryType="nt:unstructured"
                                            text="New Page"
                                            value="_blank"/>
                                    </options>
                                </D_target>
                            </items>
                        </fieldConfig>
                    </bullets>
                    <legaldisclaimer
                        jcr:primaryType="cq:Widget"
                        border="{Boolean}false"
                        collapsed="{Boolean}true"
                        collapsible="{Boolean}true"
                        title="Legal disclaimer"
                        xtype="dialogfieldset">
                        <items jcr:primaryType="cq:WidgetCollection">
                            <text
                                jcr:primaryType="cq:Widget"
                                anchor="95%"
                                hideLabel="{Boolean}true"
                                name="./footerLegalDisclaimer"
                                removeSingleParagraphContainer="{Boolean}true"
                                xtype="richtext">
                                <rtePlugins jcr:primaryType="nt:unstructured">
                                    <subsuperscript
                                        jcr:primaryType="nt:unstructured"
                                        features="*"/>
                                </rtePlugins>
                            </text>
                        </items>
                    </legaldisclaimer>
                    <peaunutdisclaimer
                        jcr:primaryType="cq:Widget"
                        border="{Boolean}false"
                        collapsed="{Boolean}true"
                        collapsible="{Boolean}true"
                        title="Peanuts disclaimer"
                        xtype="dialogfieldset">
                        <items jcr:primaryType="cq:WidgetCollection">
                            <peanutstext
                                jcr:primaryType="cq:Widget"
                                anchor="95%"
                                hideLabel="{Boolean}true"
                                name="./footerPeanutsDisclaimer"
                                removeSingleParagraphContainer="{Boolean}true"
                                xtype="richtext">
                                <rtePlugins jcr:primaryType="nt:unstructured">
                                    <subsuperscript
                                        jcr:primaryType="nt:unstructured"
                                        features="*"/>
                                </rtePlugins>
                            </peanutstext>
                        </items>
                    </peaunutdisclaimer>
                    <bulletsfield
                        jcr:primaryType="nt:unstructured"
                        ignoreData="true"
                        name="./footerbulletlinks@TypeHint"
                        value="String[]"
                        xtype="hidden"/>
                </items>
            </footer>
            <login-configuration
                jcr:primaryType="cq:Panel"
                itemId="loginConfigurationPanel"
                title="Login configuration">
                <items jcr:primaryType="cq:WidgetCollection">
                    <redirectConfiguration
                        jcr:primaryType="cq:Widget"
                        anchor="99%"
                        title="Redirect to Login Page"
                        xtype="fieldset">
                        <items jcr:primaryType="cq:WidgetCollection">
                            <redirectToLoginPage
                                jcr:primaryType="nt:unstructured"
                                fieldLabel="Redirect to login page"
                                name="./redirectToLoginPage"
                                type="checkbox"
                                xtype="selection">
                                <listeners
                                    jcr:primaryType="nt:unstructured"
                                    loadcontent="function(field,record,path){Metlife.Components.Login.loadContent(field,record,path);}"
                                    selectionchanged="function(selection, value, isChanged) { Metlife.Components.Login.selectionChanged(selection, value, isChanged);}"/>
                            </redirectToLoginPage>
                        </items>
                    </redirectConfiguration>
                    <loginPageFieldset
                        jcr:primaryType="cq:Widget"
                        anchor="99%"
                        itemId="loginPageFieldset"
                        title="Login Page Path"
                        xtype="fieldset">
                        <items jcr:primaryType="cq:WidgetCollection">
                            <loginPagePathfield
                                jcr:primaryType="nt:unstructured"
                                allowBlank="true"
                                anchor="98%"
                                fieldLabel="Select the login page"
                                itemId="loginPagePathfield"
                                linkPattern="\{0}.html"
                                name="./loginPagePath"
                                rootPath="/content/metlife"
                                rootTitle="MetLife"
                                xtype="pathfield"/>
                        </items>
                    </loginPageFieldset>
                    <modalConfiguration
                        jcr:primaryType="cq:Widget"
                        anchor="99%"
                        title="Modal Configuration"
                        xtype="fieldset">
                        <items jcr:primaryType="cq:WidgetCollection">
                            <usernamePlaceholder
                                jcr:primaryType="nt:unstructured"
                                allowBlank="false"
                                anchor="98%"
                                fieldLabel="Username Placeholder"
                                itemId="modalUsernamePlaceholder"
                                name="./usernamePlaceholder"
                                xtype="textfield"/>
                            <passwordPlaceholder
                                jcr:primaryType="nt:unstructured"
                                allowBlank="false"
                                anchor="98%"
                                fieldLabel="Password Placeholder"
                                name="./passwordPlaceholder"
                                xtype="textfield"/>
                            <forgotUsernamePassword
                                jcr:primaryType="nt:unstructured"
                                allowBlank="false"
                                anchor="98%"
                                fieldLabel="Forgot username or password link"
                                linkPattern="\{0}.html"
                                name="./forgotUsernamePassword"
                                rootPath="/content/metlife"
                                rootTitle="MetLife"
                                xtype="pathfield"/>
                            <loginButtonText
                                jcr:primaryType="nt:unstructured"
                                allowBlank="false"
                                anchor="98%"
                                fieldLabel="Submit button text"
                                name="./submitButtonText"
                                xtype="textfield"/>
                            <createNewAccount
                                jcr:primaryType="nt:unstructured"
                                allowBlank="false"
                                anchor="98%"
                                fieldLabel="Create a new Account Link"
                                linkPattern="\{0}.html"
                                name="./createNewAccount"
                                rootPath="/content/metlife"
                                rootTitle="MetLife"
                                xtype="pathfield"/>
                            <moreLoginOptions
                                jcr:primaryType="nt:unstructured"
                                allowBlank="false"
                                anchor="98%"
                                fieldLabel="More Login options"
                                linkPattern="\{0}.html"
                                name="./moreLoginOptions"
                                rootPath="/content/metlife"
                                rootTitle="MetLife"
                                xtype="pathfield"/>
                            <errorImage
                                jcr:primaryType="cq:Widget"
                                collapsed="{Boolean}true"
                                collapsible="{Boolean}true"
                                title="Error Image"
                                xtype="dialogfieldset">
                                <items jcr:primaryType="cq:WidgetCollection">
                                    <altText
                                        jcr:primaryType="cq:Widget"
                                        anchor="95%"
                                        fieldLabel="Alt Text"
                                        name="./errorImageAltText"
                                        xtype="textfield"/>
                                    <image
                                        jcr:primaryType="cq:Widget"
                                        anchor="95%"
                                        ddGroups="[media]"
                                        fieldLabel="Image"
                                        name="./login/errorImage/fileReference"
                                        rootPath="/content/dam"
                                        rootTitle="Assets"
                                        xtype="pathfield"/>
                                    <imageresourcetype
                                        jcr:primaryType="cq:Widget"
                                        ignoreData="true"
                                        name="./login/errorImage/sling:resourceType"
                                        value="foundation/components/image"
                                        xtype="hidden"/>
                                </items>
                            </errorImage>
                        </items>
                        <loginPagePath jcr:primaryType="cq:Widget"/>
                    </modalConfiguration>
                    <loginConfiguration
                        jcr:primaryType="cq:Widget"
                        anchor="99%"
                        title="Login Page Configuration"
                        xtype="fieldset">
                        <items jcr:primaryType="cq:WidgetCollection">
                            <accountType
                                jcr:primaryType="cq:Widget"
                                anchor="98%"
                                fieldLabel="Account type"
                                name="./loginAccountType"
                                type="select"
                                xtype="selection">
                                <options jcr:primaryType="cq:WidgetCollection">
                                    <individual
                                        jcr:primaryType="nt:unstructured"
                                        text="Individual"
                                        value="Individual"/>
                                    <business
                                        jcr:primaryType="nt:unstructured"
                                        text="Business"
                                        value="Business"/>
                                    <broker
                                        jcr:primaryType="nt:unstructured"
                                        text="Broker"
                                        value="Broker"/>
                                </options>
                            </accountType>
                            <usernamePlaceholder
                                jcr:primaryType="nt:unstructured"
                                allowBlank="false"
                                anchor="98%"
                                fieldLabel="Username Placeholder"
                                name="./usernameLoginPlaceholder"
                                xtype="textfield"/>
                            <passwordPlaceholder
                                jcr:primaryType="nt:unstructured"
                                allowBlank="false"
                                anchor="98%"
                                fieldLabel="Password Placeholder"
                                name="./passwordLoginPlaceholder"
                                xtype="textfield"/>
                            <forgotUsernamePassword
                                jcr:primaryType="nt:unstructured"
                                allowBlank="false"
                                anchor="98%"
                                fieldLabel="Forgot username or password link"
                                linkPattern="\{0}.html"
                                name="./forgotLoginUsernamePassword"
                                rootPath="/content/metlife"
                                rootTitle="MetLife"
                                xtype="pathfield"/>
                            <loginButtonText
                                jcr:primaryType="nt:unstructured"
                                allowBlank="false"
                                anchor="98%"
                                fieldLabel="Submit button text"
                                name="./submitLoginButtonText"
                                xtype="textfield"/>
                            <createNewAccount
                                jcr:primaryType="nt:unstructured"
                                allowBlank="false"
                                anchor="98%"
                                fieldLabel="Create a new Account Link"
                                linkPattern="\{0}.html"
                                name="./createNewLoginAccount"
                                rootPath="/content/metlife"
                                rootTitle="MetLife"
                                xtype="pathfield"/>
                        </items>
                    </loginConfiguration>
                </items>
            </login-configuration>
            <countries-and-languages
                jcr:primaryType="cq:Panel"
                itemId="countriesAndLanguagesTab"
                title="Countries &amp; Languages">
                <items jcr:primaryType="cq:WidgetCollection">
                    <links
                        jcr:primaryType="cq:Widget"
                        fieldDescription="Click the '+' to add a new link"
                        fieldLabel="Languages"
                        name="./languageSelector"
                        title=""
                        xtype="genericmultifield">
                        <fieldConfig jcr:primaryType="cq:WidgetCollection">
                            <textLink
                                jcr:primaryType="cq:Widget"
                                allowBlank="{Boolean}false"
                                anchor="90%"
                                fieldDescription=""
                                fieldLabel="Link Label"
                                name="./langSelLinkText"
                                xtype="textfield"/>
                            <linkType
                                jcr:primaryType="cq:Widget"
                                anchor="90%"
                                fieldLabel="Link Type"
                                name="./langSelLinkType"
                                type="select"
                                xtype="selection">
                                <options jcr:primaryType="cq:WidgetCollection">
                                    <internal
                                        jcr:primaryType="nt:unstructured"
                                        text="Internal"
                                        value="internal"/>
                                    <external
                                        jcr:primaryType="nt:unstructured"
                                        text="External"
                                        value="external"/>
                                </options>
                                <listeners
                                    jcr:primaryType="nt:unstructured"
                                    loadcontent="function() { &#xa;&#x9;if(this.getValue() =='undefined'){&#xa;&#x9;&#x9;this.findParentByType(&quot;panel&quot;).getComponent(2).setVisible(false);&#xa;&#x9;&#x9;this.findParentByType(&quot;panel&quot;).getComponent(3).setVisible(false);&#xa;&#x9;}else if(this.getValue() == 'internal'){&#xa;&#x9;&#x9;this.findParentByType(&quot;panel&quot;).getComponent(2).setVisible(true);&#x9;&#xa;&#x9;}else if(this.getValue() == 'external'){&#xa;&#x9;&#x9;this.findParentByType(&quot;panel&quot;).getComponent(3).setVisible(true);&#x9;&#xa;&#x9;}&#xa;}"
                                    selectionchanged="function() { &#x9;&#xa;&#x9;this.findParentByType(&quot;panel&quot;).getComponent(2).setVisible(false);&#xa;&#x9;this.findParentByType(&quot;panel&quot;).getComponent(3).setVisible(false);&#x9;&#xa;&#x9;if(this.getValue() == 'internal'){&#xa;&#x9;&#x9;this.findParentByType(&quot;panel&quot;).getComponent(2).setVisible(true);&#x9;&#xa;&#x9;&#x9;this.findParentByType(&quot;panel&quot;).getComponent(3).setVisible(false);&#x9;&#x9;&#x9;&#xa;&#x9;}else if(this.getValue() == 'external'){&#xa;&#x9;&#x9;this.findParentByType(&quot;panel&quot;).getComponent(2).setVisible(false);&#xa;&#x9;&#x9;this.findParentByType(&quot;panel&quot;).getComponent(3).setVisible(true);&#xa;&#x9;}&#xa;}"/>
                            </linkType>
                            <internalLink
                                jcr:primaryType="cq:Widget"
                                anchor="90%"
                                editable="{Boolean}false"
                                fieldDescription=""
                                fieldLabel="Path Page"
                                hidden="{Boolean}true"
                                name="./langSelInternalLink"
                                xtype="pathfield"/>
                            <externallink
                                jcr:primaryType="cq:Widget"
                                anchor="90%"
                                fieldDescription=""
                                fieldLabel="External URL"
                                hidden="{Boolean}true"
                                name="./langSelExternalLink"
                                vtype="url"
                                xtype="textfield"/>
                            <targetLink
                                jcr:primaryType="cq:Widget"
                                anchor="90%"
                                defaultValue="_self"
                                fieldDescription="&lt;br>"
                                fieldLabel="Link Target"
                                name="./langSelTargetLink"
                                type="select"
                                value="_self"
                                xtype="selection">
                                <options jcr:primaryType="cq:WidgetCollection">
                                    <self
                                        jcr:primaryType="nt:unstructured"
                                        text="Same Window"
                                        value="_self"/>
                                    <blank
                                        jcr:primaryType="nt:unstructured"
                                        text="New Window"
                                        value="_blank"/>
                                </options>
                            </targetLink>
                        </fieldConfig>
                    </links>
                    <americas
                        jcr:primaryType="cq:Widget"
                        collapsed="{Boolean}true"
                        collapsible="{Boolean}true"
                        title="Americas"
                        xtype="dialogfieldset">
                        <items jcr:primaryType="cq:WidgetCollection">
                            <label
                                jcr:primaryType="nt:unstructured"
                                allowBlank="false"
                                anchor="95%"
                                fieldLabel="Label"
                                name="./americasLabel"
                                xtype="textfield"/>
                            <countries
                                jcr:primaryType="cq:Widget"
                                addItemLabel="Add Country"
                                anchor="95%"
                                fieldDescription="Click the '+' to add a new country"
                                fieldLabel="Countries"
                                hideLabel="false"
                                maxItems="{Long}100"
                                name="./americasCountries"
                                xtype="multifield">
                                <fieldConfig
                                    jcr:primaryType="cq:Widget"
                                    xtype="multifieldpanel">
                                    <items jcr:primaryType="cq:WidgetCollection">
                                        <flag
                                            jcr:primaryType="nt:unstructured"
                                            allowBlank="false"
                                            anchor="95%"
                                            fieldLabel="Flag"
                                            key="flag"
                                            options="/etc/acs-commons/lists/metlife/countries/americas/jcr:content.list.json"
                                            type="select"
                                            validateOnBlur="true"
                                            xtype="selection">
                                            <listeners
                                                jcr:primaryType="nt:unstructured"
                                                selectionchanged="function(){&#xa;&#xa;        var tabpanel = this.findParentByType(&quot;tabpanel&quot;).getComponent(4);&#xa;&#xa;        var americas = tabpanel.getComponent(1).getComponent(1);&#xa;        var asia = tabpanel.getComponent(2).getComponent(1);&#xa;        var europe = tabpanel.getComponent(3).getComponent(1);&#xa;        var middleEastAndAfrica = tabpanel.getComponent(4).getComponent(1);&#xa;&#xa;        var countriesList = {&#xa;          country: []&#xa;        };&#xa;        var americasCountries = JSON.parse(JSON.stringify(americas.getValue()));&#xa;        var asiaCountries = JSON.parse(JSON.stringify(asia.getValue()));&#xa;        var europeCountries = JSON.parse(JSON.stringify(europe.getValue()));&#xa;        var middleEastAndAfricaCountries = JSON.parse(JSON.stringify(middleEastAndAfrica.getValue()));&#xa;&#xa;        &#xa;        for ( i=0; i&lt;americasCountries.length; i++){&#xa;            var value = JSON.parse(americasCountries[i]).flag;            &#xa;            countriesList.country.push({&#xa;              &quot;text&quot; : value,&#xa;              &quot;value&quot;  : value&#xa;            });&#xa;        }    &#xa;        for ( i=0; i&lt;asiaCountries.length; i++){&#xa;            var value = JSON.parse(asiaCountries[i]).flag;            &#xa;            countriesList.country.push({&#xa;              &quot;text&quot; : value,&#xa;              &quot;value&quot;  : value&#xa;            });&#xa;        }&#xa;        for ( i=0; i&lt;europeCountries.length; i++){&#xa;            var value = JSON.parse(europeCountries[i]).flag;            &#xa;            countriesList.country.push({&#xa;              &quot;text&quot; : value,&#xa;              &quot;value&quot;  : value&#xa;            });&#xa;        }&#xa;        for ( i=0; i&lt;middleEastAndAfricaCountries.length; i++){&#xa;            var value = JSON.parse(middleEastAndAfricaCountries[i]).flag;            &#xa;            countriesList.country.push({&#xa;              &quot;text&quot; : value,&#xa;              &quot;value&quot;  : value&#xa;            });&#xa;        }        &#xa;&#xa;        var allCountries = cleanup(countriesList.country, 'value');&#xa;&#xa;        var defaultCountry = this.findParentByType(&quot;tabpanel&quot;).getComponent(4).getComponent(5);&#xa;        defaultCountry.setOptions(allCountries);&#xa;      &#xa;}"/>
                                        </flag>
                                        <label
                                            jcr:primaryType="nt:unstructured"
                                            allowBlank="true"
                                            anchor="95%"
                                            fieldLabel="Label"
                                            key="countryName"
                                            xtype="textfield"/>
                                        <link
                                            jcr:primaryType="cq:Widget"
                                            allowBlank="false"
                                            anchor="95%"
                                            fieldLabel="Link"
                                            key="link"
                                            linkPattern="\{0}.html"
                                            xtype="pathfield"/>
                                    </items>
                                </fieldConfig>
                            </countries>
                        </items>
                    </americas>
                    <asia
                        jcr:primaryType="cq:Widget"
                        collapsed="{Boolean}true"
                        collapsible="{Boolean}true"
                        title="Asia"
                        xtype="dialogfieldset">
                        <items jcr:primaryType="cq:WidgetCollection">
                            <label
                                jcr:primaryType="nt:unstructured"
                                allowBlank="false"
                                anchor="95%"
                                fieldLabel="Label"
                                name="./asiaLabel"
                                xtype="textfield"/>
                            <countries
                                jcr:primaryType="cq:Widget"
                                addItemLabel="Add Country"
                                anchor="95%"
                                fieldDescription="Click the '+' to add a new country"
                                fieldLabel="Countries"
                                hideLabel="false"
                                maxItems="{Long}100"
                                name="./asiaCountries"
                                xtype="multifield">
                                <fieldConfig
                                    jcr:primaryType="cq:Widget"
                                    xtype="multifieldpanel">
                                    <items jcr:primaryType="cq:WidgetCollection">
                                        <flag
                                            jcr:primaryType="nt:unstructured"
                                            allowBlank="false"
                                            anchor="95%"
                                            fieldLabel="Flag"
                                            key="flag"
                                            options="/etc/acs-commons/lists/metlife/countries/asia/jcr:content.list.json"
                                            type="select"
                                            validateOnBlur="true"
                                            xtype="selection">
                                            <listeners
                                                jcr:primaryType="nt:unstructured"
                                                selectionchanged="function(){&#xa;&#xa;        var tabpanel = this.findParentByType(&quot;tabpanel&quot;).getComponent(4);&#xa;&#xa;        var americas = tabpanel.getComponent(1).getComponent(1);&#xa;        var asia = tabpanel.getComponent(2).getComponent(1);&#xa;        var europe = tabpanel.getComponent(3).getComponent(1);&#xa;        var middleEastAndAfrica = tabpanel.getComponent(4).getComponent(1);&#xa;&#xa;        var countriesList = {&#xa;          country: []&#xa;        };&#xa;        var americasCountries = JSON.parse(JSON.stringify(americas.getValue()));&#xa;        var asiaCountries = JSON.parse(JSON.stringify(asia.getValue()));&#xa;        var europeCountries = JSON.parse(JSON.stringify(europe.getValue()));&#xa;        var middleEastAndAfricaCountries = JSON.parse(JSON.stringify(middleEastAndAfrica.getValue()));&#xa;&#xa;        &#xa;        for ( i=0; i&lt;americasCountries.length; i++){&#xa;            var value = JSON.parse(americasCountries[i]).flag;            &#xa;            countriesList.country.push({&#xa;              &quot;text&quot; : value,&#xa;              &quot;value&quot;  : value&#xa;            });&#xa;        }    &#xa;        for ( i=0; i&lt;asiaCountries.length; i++){&#xa;            var value = JSON.parse(asiaCountries[i]).flag;            &#xa;            countriesList.country.push({&#xa;              &quot;text&quot; : value,&#xa;              &quot;value&quot;  : value&#xa;            });&#xa;        }&#xa;        for ( i=0; i&lt;europeCountries.length; i++){&#xa;            var value = JSON.parse(europeCountries[i]).flag;            &#xa;            countriesList.country.push({&#xa;              &quot;text&quot; : value,&#xa;              &quot;value&quot;  : value&#xa;            });&#xa;        }&#xa;        for ( i=0; i&lt;middleEastAndAfricaCountries.length; i++){&#xa;            var value = JSON.parse(middleEastAndAfricaCountries[i]).flag;            &#xa;            countriesList.country.push({&#xa;              &quot;text&quot; : value,&#xa;              &quot;value&quot;  : value&#xa;            });&#xa;        }        &#xa;&#xa;        var allCountries = cleanup(countriesList.country, 'value');&#xa;&#xa;        var defaultCountry = this.findParentByType(&quot;tabpanel&quot;).getComponent(4).getComponent(5);&#xa;        defaultCountry.setOptions(allCountries);&#xa;      &#xa;}"/>
                                        </flag>
                                        <label
                                            jcr:primaryType="nt:unstructured"
                                            allowBlank="true"
                                            anchor="95%"
                                            fieldLabel="Label"
                                            key="countryName"
                                            xtype="textfield"/>
                                        <link
                                            jcr:primaryType="cq:Widget"
                                            allowBlank="false"
                                            anchor="95%"
                                            fieldLabel="Link"
                                            key="link"
                                            linkPattern="\{0}.html"
                                            xtype="pathfield"/>
                                    </items>
                                </fieldConfig>
                            </countries>
                        </items>
                    </asia>
                    <europe
                        jcr:primaryType="cq:Widget"
                        collapsed="{Boolean}true"
                        collapsible="{Boolean}true"
                        title="Europe"
                        xtype="dialogfieldset">
                        <items jcr:primaryType="cq:WidgetCollection">
                            <label
                                jcr:primaryType="nt:unstructured"
                                allowBlank="false"
                                anchor="95%"
                                fieldLabel="Label"
                                name="./europeLabel"
                                xtype="textfield"/>
                            <countries
                                jcr:primaryType="cq:Widget"
                                addItemLabel="Add Country"
                                anchor="95%"
                                fieldDescription="Click the '+' to add a new country"
                                fieldLabel="Countries"
                                hideLabel="false"
                                maxItems="{Long}100"
                                name="./europeCountries"
                                xtype="multifield">
                                <fieldConfig
                                    jcr:primaryType="cq:Widget"
                                    xtype="multifieldpanel">
                                    <items jcr:primaryType="cq:WidgetCollection">
                                        <flag
                                            jcr:primaryType="nt:unstructured"
                                            allowBlank="false"
                                            anchor="95%"
                                            fieldLabel="Flag"
                                            key="flag"
                                            options="/etc/acs-commons/lists/metlife/countries/europe/jcr:content.list.json"
                                            type="select"
                                            validateOnBlur="true"
                                            xtype="selection">
                                            <listeners
                                                jcr:primaryType="nt:unstructured"
                                                selectionchanged="function(){&#xa;&#xa;        var tabpanel = this.findParentByType(&quot;tabpanel&quot;).getComponent(4);&#xa;&#xa;        var americas = tabpanel.getComponent(1).getComponent(1);&#xa;        var asia = tabpanel.getComponent(2).getComponent(1);&#xa;        var europe = tabpanel.getComponent(3).getComponent(1);&#xa;        var middleEastAndAfrica = tabpanel.getComponent(4).getComponent(1);&#xa;&#xa;        var countriesList = {&#xa;          country: []&#xa;        };&#xa;        var americasCountries = JSON.parse(JSON.stringify(americas.getValue()));&#xa;        var asiaCountries = JSON.parse(JSON.stringify(asia.getValue()));&#xa;        var europeCountries = JSON.parse(JSON.stringify(europe.getValue()));&#xa;        var middleEastAndAfricaCountries = JSON.parse(JSON.stringify(middleEastAndAfrica.getValue()));&#xa;&#xa;        &#xa;        for ( i=0; i&lt;americasCountries.length; i++){&#xa;            var value = JSON.parse(americasCountries[i]).flag;            &#xa;            countriesList.country.push({&#xa;              &quot;text&quot; : value,&#xa;              &quot;value&quot;  : value&#xa;            });&#xa;        }    &#xa;        for ( i=0; i&lt;asiaCountries.length; i++){&#xa;            var value = JSON.parse(asiaCountries[i]).flag;            &#xa;            countriesList.country.push({&#xa;              &quot;text&quot; : value,&#xa;              &quot;value&quot;  : value&#xa;            });&#xa;        }&#xa;        for ( i=0; i&lt;europeCountries.length; i++){&#xa;            var value = JSON.parse(europeCountries[i]).flag;            &#xa;            countriesList.country.push({&#xa;              &quot;text&quot; : value,&#xa;              &quot;value&quot;  : value&#xa;            });&#xa;        }&#xa;        for ( i=0; i&lt;middleEastAndAfricaCountries.length; i++){&#xa;            var value = JSON.parse(middleEastAndAfricaCountries[i]).flag;            &#xa;            countriesList.country.push({&#xa;              &quot;text&quot; : value,&#xa;              &quot;value&quot;  : value&#xa;            });&#xa;        }        &#xa;&#xa;        var allCountries = cleanup(countriesList.country, 'value');&#xa;&#xa;        var defaultCountry = this.findParentByType(&quot;tabpanel&quot;).getComponent(4).getComponent(5);&#xa;        defaultCountry.setOptions(allCountries);&#xa;      &#xa;}"/>
                                        </flag>
                                        <label
                                            jcr:primaryType="nt:unstructured"
                                            allowBlank="true"
                                            anchor="95%"
                                            fieldLabel="Label"
                                            key="countryName"
                                            xtype="textfield"/>
                                        <link
                                            jcr:primaryType="cq:Widget"
                                            allowBlank="false"
                                            anchor="95%"
                                            fieldLabel="Link"
                                            key="link"
                                            linkPattern="\{0}.html"
                                            xtype="pathfield"/>
                                    </items>
                                </fieldConfig>
                            </countries>
                        </items>
                    </europe>
                    <middleEastAndAfrica
                        jcr:primaryType="cq:Widget"
                        collapsed="{Boolean}true"
                        collapsible="{Boolean}true"
                        title="Middle East and Africa"
                        xtype="dialogfieldset">
                        <items jcr:primaryType="cq:WidgetCollection">
                            <label
                                jcr:primaryType="nt:unstructured"
                                allowBlank="false"
                                anchor="95%"
                                fieldLabel="Label"
                                name="./middleEastAndAfricaLabel"
                                xtype="textfield"/>
                            <countries
                                jcr:primaryType="cq:Widget"
                                addItemLabel="Add Country"
                                anchor="95%"
                                fieldDescription="Click the '+' to add a new country"
                                fieldLabel="Countries"
                                hideLabel="false"
                                maxItems="{Long}100"
                                name="./middleEastAndAfricaCountries"
                                xtype="multifield">
                                <fieldConfig
                                    jcr:primaryType="cq:Widget"
                                    xtype="multifieldpanel">
                                    <items jcr:primaryType="cq:WidgetCollection">
                                        <flag
                                            jcr:primaryType="nt:unstructured"
                                            allowBlank="false"
                                            anchor="95%"
                                            fieldLabel="Flag"
                                            key="flag"
                                            options="/etc/acs-commons/lists/metlife/countries/middleEastAndAfrica/jcr:content.list.json"
                                            type="select"
                                            validateOnBlur="true"
                                            xtype="selection">
                                            <listeners
                                                jcr:primaryType="nt:unstructured"
                                                selectionchanged="function(){&#xa;&#xa;        var tabpanel = this.findParentByType(&quot;tabpanel&quot;).getComponent(4);&#xa;&#xa;        var americas = tabpanel.getComponent(1).getComponent(1);&#xa;        var asia = tabpanel.getComponent(2).getComponent(1);&#xa;        var europe = tabpanel.getComponent(3).getComponent(1);&#xa;        var middleEastAndAfrica = tabpanel.getComponent(4).getComponent(1);&#xa;&#xa;        var countriesList = {&#xa;          country: []&#xa;        };&#xa;        var americasCountries = JSON.parse(JSON.stringify(americas.getValue()));&#xa;        var asiaCountries = JSON.parse(JSON.stringify(asia.getValue()));&#xa;        var europeCountries = JSON.parse(JSON.stringify(europe.getValue()));&#xa;        var middleEastAndAfricaCountries = JSON.parse(JSON.stringify(middleEastAndAfrica.getValue()));&#xa;&#xa;        &#xa;        for ( i=0; i&lt;americasCountries.length; i++){&#xa;            var value = JSON.parse(americasCountries[i]).flag;            &#xa;            countriesList.country.push({&#xa;              &quot;text&quot; : value,&#xa;              &quot;value&quot;  : value&#xa;            });&#xa;        }    &#xa;        for ( i=0; i&lt;asiaCountries.length; i++){&#xa;            var value = JSON.parse(asiaCountries[i]).flag;            &#xa;            countriesList.country.push({&#xa;              &quot;text&quot; : value,&#xa;              &quot;value&quot;  : value&#xa;            });&#xa;        }&#xa;        for ( i=0; i&lt;europeCountries.length; i++){&#xa;            var value = JSON.parse(europeCountries[i]).flag;            &#xa;            countriesList.country.push({&#xa;              &quot;text&quot; : value,&#xa;              &quot;value&quot;  : value&#xa;            });&#xa;        }&#xa;        for ( i=0; i&lt;middleEastAndAfricaCountries.length; i++){&#xa;            var value = JSON.parse(middleEastAndAfricaCountries[i]).flag;            &#xa;            countriesList.country.push({&#xa;              &quot;text&quot; : value,&#xa;              &quot;value&quot;  : value&#xa;            });&#xa;        }        &#xa;&#xa;        var allCountries = cleanup(countriesList.country, 'value');&#xa;&#xa;        var defaultCountry = this.findParentByType(&quot;tabpanel&quot;).getComponent(4).getComponent(5);&#xa;        defaultCountry.setOptions(allCountries);&#xa;      &#xa;}"/>
                                        </flag>
                                        <label
                                            jcr:primaryType="nt:unstructured"
                                            allowBlank="true"
                                            anchor="95%"
                                            fieldLabel="Label"
                                            key="countryName"
                                            xtype="textfield"/>
                                        <link
                                            jcr:primaryType="cq:Widget"
                                            allowBlank="false"
                                            anchor="95%"
                                            fieldLabel="Link"
                                            key="link"
                                            linkPattern="\{0}.html"
                                            xtype="pathfield"/>
                                    </items>
                                </fieldConfig>
                            </countries>
                        </items>
                    </middleEastAndAfrica>
                    <defaultCountry
                        jcr:primaryType="nt:unstructured"
                        allowBlank="false"
                        anchor="95%"
                        fieldLabel="Default Country"
                        name="./defaultCountry"
                        optionsProvider="function(path, record){ return Metlife.Global.Countries.defaultCountryProvider(path,record, this);}"
                        type="select"
                        xtype="selection"/>
                    <defaultCountryLabel
                        jcr:primaryType="nt:unstructured"
                        allowBlank="false"
                        anchor="95%"
                        fieldLabel="Default Country Label"
                        name="./defaultLabelCountry"
                        xtype="textfield"/>
                    <newsroomNamespaces
                        jcr:primaryType="cq:Widget"
                        fieldDescription="This namespaces are on: /etc/tags/metlife"
                        fieldLabel="Namespace"
                        fieldSublabel="Select Tag namespace"
                        name="./newsroomNamespaces"
                        optionsProvider="function(path , record) {&#xa;    return Metlife.Components.NewsRoomArticle.NameSpacesOptions();&#xa;&#xa;}"
                        type="select"
                        xtype="selection"/>
                </items>
            </countries-and-languages>
            <cookieBannerConfiguration
                jcr:primaryType="cq:Panel"
                title="Cookie Banner Configuration">
                <items jcr:primaryType="cq:WidgetCollection">
                    <cookieBannerDescription
                        jcr:primaryType="cq:Widget"
                        allowBlank="false"
                        fieldLabel="Description"
                        name="./cookieBannerDescription"
                        xtype="richtext"/>
                    <cookieBannerAcceptanceButtonLabel
                        jcr:primaryType="cq:Widget"
                        allowBlank="false"
                        fieldLabel="Button Label"
                        name="./cookieBannerAcceptanceButtonLabel"
                        xtype="textfield"/>
                    <cookieBannerExpiryPeriod
                        jcr:primaryType="cq:Widget"
                        allowBlank="false"
                        enableKeyEvents="{Boolean}true"
                        fieldDescription="Please enter a number greater than 364 (Days)."
                        fieldLabel="Expiry Period"
                        name="./cookieBannerExpiryPeriod"
                        xtype="numberfield"/>
                    <cookieBannerAcceptance
                        jcr:primaryType="cq:Widget"
                        allowBlank="true"
                        fieldLabel="Cookie Acceptance"
                        name="./cookieBannerAcceptance"
                        type="checkbox"
                        xtype="selection"/>
                    <cookieBannerAllowImmediateAnalytics
                        jcr:primaryType="cq:Widget"
                        allowBlank="true"
                        fieldLabel="Allow Immediate Analytics"
                        name="./cookieBannerAllowImmediateAnalytics"
                        type="checkbox"
                        xtype="selection"/>
                    <cookieBannerTitle
                        jcr:primaryType="cq:Widget"
                        allowBlank="true"
                        fieldLabel="Title"
                        name="./cookieBannerTitle"
                        xtype="textfield"/>
                </items>
            </cookieBannerConfiguration>
            <socialmedia
                jcr:primaryType="cq:Panel"
                title="Social Media">
                <items jcr:primaryType="cq:WidgetCollection">
                    <followuslabel
                        jcr:primaryType="cq:Widget"
                        fieldLabel="Follow Us Label"
                        name="./followuslabel"
                        xtype="textfield"/>
                    <medialinks
                        jcr:primaryType="cq:Widget"
                        addItemLabel="Add social media platforms"
                        fieldDescription="Click the '+' to add a new social media platforms"
                        fieldLabel="Social media platforms"
                        hideLabel="false"
                        name="./footersociallinks"
                        xtype="multifield">
                        <fieldConfig
                            jcr:primaryType="cq:Widget"
                            xtype="multifieldpanel">
                            <items jcr:primaryType="cq:WidgetCollection">
                                <A_icon
                                    jcr:primaryType="nt:unstructured"
                                    allowBlank="false"
                                    anchor="100%"
                                    fieldLabel="Icon"
                                    key="socialmediaimage"
                                    name="./footersocialimages/fileReferences"
                                    rootPath="/content/dam"
                                    validateOnBlur="true"
                                    xtype="pathfield"/>
                                <C_pages
                                    jcr:primaryType="cq:Widget"
                                    allowBlank="false"
                                    anchor="100%"
                                    fieldLabel="URL"
                                    key="path"
                                    linkPattern="\{0}.html"
                                    rootPath="/content/metlife"
                                    xtype="pathfield"/>
                                <alttext
                                    jcr:primaryType="nt:unstructured"
                                    allowBlank="false"
                                    anchor="100%"
                                    fieldLabel="Alt Text"
                                    key="altText"
                                    validateOnBlur="true"
                                    xtype="textfield"/>
                                <D_target
                                    jcr:primaryType="cq:Widget"
                                    allowBlank="false"
                                    defaultValue="_self"
                                    fieldLabel="Target"
                                    key="target"
                                    type="select"
                                    xtype="selection">
                                    <options jcr:primaryType="cq:WidgetCollection">
                                        <self
                                            jcr:primaryType="nt:unstructured"
                                            text="Same Page"
                                            value="_self"/>
                                        <blank
                                            jcr:primaryType="nt:unstructured"
                                            text="New Page"
                                            value="_blank"/>
                                    </options>
                                </D_target>
                            </items>
                        </fieldConfig>
                    </medialinks>
                    <medialinksfield
                        jcr:primaryType="nt:unstructured"
                        ignoreData="true"
                        name="./footersociallinks@TypeHint"
                        value="String[]"
                        xtype="hidden"/>
                    <imageNode
                        jcr:primaryType="nt:unstructured"
                        ignoreData="true"
                        name="./footersocialimages/sling:resourceType"
                        value="xumakbase/components/section/base"
                        xtype="hidden"/>
                </items>
            </socialmedia>
            <footer-farm-links
                jcr:primaryType="cq:Panel"
                title="Footer - Farm Links">
                <items jcr:primaryType="cq:WidgetCollection">
                    <famrs
                        jcr:primaryType="cq:Widget"
                        addItemLabel="Add Section"
                        anchor="95%"
                        fieldDescription="Click the '+' to add a new section"
                        fieldLabel="Section"
                        hideLabel="false"
                        maxItems="{Long}5"
                        name="./farmLinkSecction"
                        xtype="multifield">
                        <fieldConfig
                            jcr:primaryType="cq:Widget"
                            xtype="multifieldpanel">
                            <items jcr:primaryType="cq:WidgetCollection">
                                <label
                                    jcr:primaryType="nt:unstructured"
                                    allowBlank="false"
                                    anchor="95%"
                                    fieldLabel="Label"
                                    key="label"
                                    validateOnBlur="true"
                                    xtype="textfield"/>
                                <links
                                    jcr:primaryType="cq:Widget"
                                    addItemLabel="Add Link"
                                    fieldDescription="Click the '+' to add a new link"
                                    fieldLabel="Links"
                                    key="links"
                                    maxItems="{Long}7"
                                    minItems="{Long}1"
                                    name="./farmLinks"
                                    xtype="multifield">
                                    <fieldConfig
                                        jcr:primaryType="cq:Widget"
                                        xtype="multifieldpanel">
                                        <items jcr:primaryType="cq:WidgetCollection">
                                            <label
                                                jcr:primaryType="nt:unstructured"
                                                allowBlank="false"
                                                anchor="98%"
                                                fieldLabel="Label"
                                                key="label"
                                                validateOnBlur="true"
                                                xtype="textfield"/>
                                            <link
                                                jcr:primaryType="cq:Widget"
                                                allowBlank="false"
                                                anchor="98%"
                                                fieldLabel="Link"
                                                key="link"
                                                linkPattern="\{0}.html"
                                                xtype="pathfield"/>
                                            <linkTarget
                                                jcr:primaryType="cq:Widget"
                                                allowBlank="false"
                                                anchor="98%"
                                                fieldLabel="Target"
                                                key="target"
                                                type="select"
                                                xtype="selection">
                                                <options jcr:primaryType="cq:WidgetCollection">
                                                    <self
                                                        jcr:primaryType="nt:unstructured"
                                                        text="same window"
                                                        value="_self"/>
                                                    <newWindow
                                                        jcr:primaryType="nt:unstructured"
                                                        text="new window"
                                                        value="_blank"/>
                                                </options>
                                            </linkTarget>
                                        </items>
                                    </fieldConfig>
                                </links>
                            </items>
                        </fieldConfig>
                    </famrs>
                </items>
            </footer-farm-links>
            <chat-and-online-opinion
                jcr:primaryType="cq:Panel"
                title="Chat &amp; Online Opinion">
                <items jcr:primaryType="cq:WidgetCollection">
                    <online-opinion-config
                        jcr:primaryType="cq:Widget"
                        collapsed="{Boolean}false"
                        collapsible="{Boolean}true"
                        title="Online Opinion Configuration"
                        xtype="dialogfieldset">
                        <items jcr:primaryType="cq:WidgetCollection">
                            <active
                                jcr:primaryType="cq:Widget"
                                fieldLabel="Active"
                                name="./onlineOpinionIsActive"
                                type="checkbox"
                                xtype="selection"/>
                            <feedbackMobileLabel
                                jcr:primaryType="cq:Widget"
                                allowBlank="false"
                                anchor="90%"
                                fieldLabel="Mobile Feedback Label"
                                name="./onlineOpinionMobileLabel"
                                xtype="textfield"/>
                        </items>
                    </online-opinion-config>
                    <chat-config
                        jcr:primaryType="cq:Widget"
                        collapsed="{Boolean}true"
                        collapsible="{Boolean}true"
                        title="Chat Configuration"
                        xtype="dialogfieldset">
                        <items jcr:primaryType="cq:WidgetCollection">
                            <isactive
                                jcr:primaryType="cq:Widget"
                                allowBlank="true"
                                fieldLabel="Chat Active"
                                name="./liveChatActive"
                                type="checkbox"
                                xtype="selection"/>
                            <buttons
                                jcr:primaryType="cq:Widget"
                                addItemLabel="Add Button"
                                anchor="95%"
                                fieldDescription="Click the '+' to add a new button"
                                fieldLabel="Buttons"
                                name="./liveChatButtons"
                                xtype="multifield">
                                <fieldConfig
                                    jcr:primaryType="cq:Widget"
                                    xtype="multifieldpanel">
                                    <items jcr:primaryType="cq:WidgetCollection">
                                        <name
                                            jcr:primaryType="nt:unstructured"
                                            allowBlank="false"
                                            anchor="95%"
                                            fieldLabel="Name"
                                            key="name"
                                            xtype="textfield"/>
                                        <id
                                            jcr:primaryType="cq:Widget"
                                            allowBlank="false"
                                            anchor="95%"
                                            fieldLabel="ID"
                                            key="id"
                                            xtype="textfield"/>
                                    </items>
                                </fieldConfig>
                            </buttons>
                            <specialties-hint
                                jcr:primaryType="nt:unstructured"
                                ignoreData="true"
                                name="./liveChatButtons@TypeHint"
                                value="String[]"
                                xtype="hidden"/>
                        </items>
                    </chat-config>
                </items>
            </chat-and-online-opinion>
            <google-analytics
                jcr:primaryType="cq:Panel"
                title="Google Analytics">
                <items jcr:primaryType="cq:WidgetCollection">
                    <apply
                        jcr:primaryType="cq:Widget"
                        allowBlank="true"
                        fieldLabel="Apply"
                        name="./apply"
                        type="checkbox"
                        xtype="selection"/>
                    <trackingId
                        jcr:primaryType="cq:Widget"
                        allowBlank="false"
                        anchor="95%"
                        fieldDescription="Add the UA-XXXXX-Y Key"
                        fieldLabel="Tracking ID"
                        name="./trackingId"
                        xtype="textfield"/>
                </items>
            </google-analytics>
        </items>
    </items>
</jcr:root>
